setup.py
metro_cost/__init__.py
metro_cost.egg-info/PKG-INFO
metro_cost.egg-info/SOURCES.txt
metro_cost.egg-info/dependency_links.txt
metro_cost.egg-info/not-zip-safe
metro_cost.egg-info/requires.txt
metro_cost.egg-info/top_level.txt