Metadata-Version: 1.0
Name: metro-cost
Version: 0.1
Summary: A model that can predict the cost of metro construction
Home-page: http://github.com/storborg/metro_cost
Author: Manolo
Author-email: manolo@example.com
License: MIT
Platform: UNKNOWN
